yaml_scripts/__init__.py
yaml_scripts/__main__.py
yaml_scripts/build.py
yaml_scripts/cli.py
yaml_scripts/display.py
yaml_scripts-0.1.1.post1.dist-info/entry_points.txt
yaml_scripts-0.1.1.post1.dist-info/METADATA
yaml_scripts-0.1.1.post1.dist-info/WHEEL
yaml_scripts-0.1.1.post1.dist-info/RECORD
