Metadata-Version: 2.1
Name: yaml-scripts
Version: 0.1.1.post1
Summary: Creating windows auto install scripts from YAML config files
Home-page: https://github.com/arnos-stuff/yaml-scripts
Author: arnos-stuff
Author-email: bcda0276@gmail.com
Requires-Python: >=3.9,<4.0
Classifier: Programming Language :: Python :: 3
Classifier: Programming Language :: Python :: 3.9
Classifier: Programming Language :: Python :: 3.10
Classifier: Programming Language :: Python :: 3.11
Requires-Dist: ix-cli (>=0.1.2,<0.2.0)
Requires-Dist: yaml-setup (>=0.1.1,<0.2.0)
